{"resupplyLockers": [], "spawnPoints": [{"classname": "info_player_teamspawn", "origin": "256 -960 24", "TeamNum": "2", "id": "4059", "angles": "0 90 0"}, {"origin": "512 832 24", "classname": "info_player_teamspawn", "angles": "0 270 0", "TeamNum": "3", "targetname": "blue_player_spawn", "id": "4063"}, {"origin": "384 832 24", "classname": "info_player_teamspawn", "angles": "0 270 0", "TeamNum": "3", "targetname": "blue_player_spawn", "id": "4065"}, {"origin": "256 832 24", "classname": "info_player_teamspawn", "angles": "0 270 0", "TeamNum": "3", "targetname": "blue_player_spawn", "id": "4067"}, {"origin": "128 832 24", "classname": "info_player_teamspawn", "angles": "0 270 0", "TeamNum": "3", "targetname": "blue_player_spawn", "id": "4069"}, {"origin": "0 832 24", "classname": "info_player_teamspawn", "angles": "0 270 0", "TeamNum": "3", "targetname": "blue_player_spawn", "id": "4071"}, {"origin": "256 960 24", "classname": "info_player_teamspawn", "angles": "0 270 0", "TeamNum": "3", "targetname": "blue_player_spawn", "id": "4073"}, {"origin": "128 960 24", "classname": "info_player_teamspawn", "angles": "0 270 0", "TeamNum": "3", "targetname": "blue_player_spawn", "id": "4075"}, {"origin": "384 960 24", "classname": "info_player_teamspawn", "angles": "0 270 0", "TeamNum": "3", "targetname": "blue_player_spawn", "id": "4077"}, {"origin": "-128 960 24", "classname": "info_player_teamspawn", "angles": "0 270 0", "TeamNum": "3", "targetname": "blue_player_spawn", "id": "4079"}, {"origin": "-128 832 24", "classname": "info_player_teamspawn", "angles": "0 270 0", "TeamNum": "3", "targetname": "blue_player_spawn", "id": "4081"}, {"origin": "-256 832 24", "classname": "info_player_teamspawn", "angles": "0 270 0", "TeamNum": "3", "targetname": "blue_player_spawn", "id": "4083"}, {"origin": "-384 832 24", "classname": "info_player_teamspawn", "angles": "0 270 0", "TeamNum": "3", "targetname": "blue_player_spawn", "id": "4085"}, {"origin": "-512 832 24", "classname": "info_player_teamspawn", "angles": "0 270 0", "TeamNum": "3", "targetname": "blue_player_spawn", "id": "4087"}, {"origin": "-384 960 24", "classname": "info_player_teamspawn", "angles": "0 270 0", "TeamNum": "3", "targetname": "blue_player_spawn", "id": "4089"}, {"origin": "-256 960 24", "classname": "info_player_teamspawn", "angles": "0 270 0", "TeamNum": "3", "targetname": "blue_player_spawn", "id": "4091"}, {"classname": "info_player_teamspawn", "origin": "-512 -832 24", "TeamNum": "2", "id": "4093", "angles": "0 90 0"}, {"classname": "info_player_teamspawn", "origin": "-384 -832 24", "TeamNum": "2", "id": "4095", "angles": "0 90 0"}, {"classname": "info_player_teamspawn", "origin": "-384 -960 24", "TeamNum": "2", "id": "4097", "angles": "0 90 0"}, {"classname": "info_player_teamspawn", "origin": "-256 -960 24", "TeamNum": "2", "id": "4099", "angles": "0 90 0"}, {"classname": "info_player_teamspawn", "origin": "-128 -960 24", "TeamNum": "2", "id": "4101", "angles": "0 90 0"}, {"classname": "info_player_teamspawn", "origin": "-128 -832 24", "TeamNum": "2", "id": "4103", "angles": "0 90 0"}, {"classname": "info_player_teamspawn", "origin": "-256 -832 24", "TeamNum": "2", "id": "4105", "angles": "0 90 0"}, {"classname": "info_player_teamspawn", "origin": "0 -832 24", "TeamNum": "2", "id": "4107", "angles": "0 90 0"}, {"classname": "info_player_teamspawn", "origin": "0 -960 24", "TeamNum": "2", "id": "4109", "angles": "0 90 0"}, {"classname": "info_player_teamspawn", "origin": "128 -960 24", "TeamNum": "2", "id": "4111", "angles": "0 90 0"}, {"classname": "info_player_teamspawn", "origin": "256 -832 24", "TeamNum": "2", "id": "4113", "angles": "0 90 0"}, {"classname": "info_player_teamspawn", "origin": "128 -832 24", "TeamNum": "2", "id": "4115", "angles": "0 90 0"}, {"classname": "info_player_teamspawn", "origin": "384 -832 24", "TeamNum": "2", "id": "4117", "angles": "0 90 0"}, {"classname": "info_player_teamspawn", "origin": "512 -832 24", "TeamNum": "2", "id": "4119", "angles": "0 90 0"}, {"classname": "info_player_teamspawn", "origin": "384 -960 24", "TeamNum": "2", "id": "4121", "angles": "0 90 0"}, {"origin": "0 960 24", "classname": "info_player_teamspawn", "angles": "0 270 0", "TeamNum": "3", "targetname": "blue_player_spawn", "id": "4688"}], "dimensions": [[-2272.0, -2568.0, -650.0], [3024.0, 3024.0, 1528.0], {"screenHeight": 1080, "scale": 6, "screenWidth": 1920}, {"y": 228.0, "x": 376.0, "z": 1528.0}], "fileHash": "a195b6f47cd18409e4aadb82745481c6", "normalizedMapName": "tfdb_partyisland", "tournamentStage": null, "cameras": [{"origin": "1572 104 392", "fov": "90", "defaultwelcome": "1", "classname": "info_observer_point", "angles": "10 185 0", "targetname": "spec_welcome", "id": "4055"}], "ammoPacks": [], "healthKits": [{"origin": "-384 -640 1", "StartDisabled": "1", "classname": "item_healthkit_small", "angles": "0 0 0", "targetname": "medpac2", "id": "15263"}, {"origin": "-384 -384 1", "StartDisabled": "1", "classname": "item_healthkit_small", "angles": "0 0 0", "targetname": "medpac1", "id": "15250"}, {"origin": "-128 -384 1", "StartDisabled": "1", "classname": "item_healthkit_small", "angles": "0 0 0", "targetname": "medpac3", "id": "15269"}, {"origin": "-128 -640 1", "StartDisabled": "1", "classname": "item_healthkit_small", "angles": "0 0 0", "targetname": "medpac4", "id": "15271"}, {"origin": "128 -640 1", "StartDisabled": "1", "classname": "item_healthkit_small", "angles": "0 0 0", "targetname": "medpac6", "id": "15279"}, {"origin": "128 -384 1", "StartDisabled": "1", "classname": "item_healthkit_small", "angles": "0 0 0", "targetname": "medpac5", "id": "15277"}, {"origin": "384 -384 1", "StartDisabled": "1", "classname": "item_healthkit_small", "angles": "0 0 0", "targetname": "medpac7", "id": "15285"}, {"origin": "384 -640 1", "StartDisabled": "1", "classname": "item_healthkit_small", "angles": "0 0 0", "targetname": "medpac8", "id": "15287"}, {"origin": "-384 384 1", "StartDisabled": "1", "classname": "item_healthkit_small", "angles": "0 0 0", "targetname": "medpac2b", "id": "15407"}, {"origin": "-384 640 1", "StartDisabled": "1", "classname": "item_healthkit_small", "angles": "0 0 0", "targetname": "medpac1b", "id": "15409"}, {"origin": "-128 640 1", "StartDisabled": "1", "classname": "item_healthkit_small", "angles": "0 0 0", "targetname": "medpac3b", "id": "15411"}, {"origin": "-128 384 1", "StartDisabled": "1", "classname": "item_healthkit_small", "angles": "0 0 0", "targetname": "medpac4b", "id": "15413"}, {"origin": "128 384 1", "StartDisabled": "1", "classname": "item_healthkit_small", "angles": "0 0 0", "targetname": "medpac6b", "id": "15415"}, {"origin": "128 640 1", "StartDisabled": "1", "classname": "item_healthkit_small", "angles": "0 0 0", "targetname": "medpac5b", "id": "15417"}, {"origin": "384 640 1", "StartDisabled": "1", "classname": "item_healthkit_small", "angles": "0 0 0", "targetname": "medpac7b", "id": "15419"}, {"origin": "384 384 1", "StartDisabled": "1", "classname": "item_healthkit_small", "angles": "0 0 0", "targetname": "medpac8b", "id": "15421"}], "entityCount": 293, "version": 166, "containsHalloweenProps": false, "skyboxCamera": [4096.0, 4096.0, -1012.0], "briefCases": [], "controlPoints": []}